pydantic_filters/__init__.py
pydantic_filters/_types.py
pydantic_filters/drivers/__init__.py
pydantic_filters/drivers/sqlalchemy/__init__.py
pydantic_filters/drivers/sqlalchemy/_exceptions.py
pydantic_filters/drivers/sqlalchemy/_main.py
pydantic_filters/drivers/sqlalchemy/_mapping.py
pydantic_filters/drivers/sqlalchemy/_operators.py
pydantic_filters/filter/__init__.py
pydantic_filters/filter/_base.py
pydantic_filters/filter/_config.py
pydantic_filters/filter/_definer.py
pydantic_filters/filter/_extractors.py
pydantic_filters/filter/_fields.py
pydantic_filters/filter/_meta.py
pydantic_filters/filter/_types.py
pydantic_filters/pagination/__init__.py
pydantic_filters/pagination/_base.py
pydantic_filters/plugins/__init__.py
pydantic_filters/plugins/_utils.py
pydantic_filters/plugins/fastapi.py
pydantic_filters/sort/__init__.py
pydantic_filters/sort/_base.py
pydantic_filters/sort/_types.py
pydantic_filters-0.3.4.dist-info/LICENSE
pydantic_filters-0.3.4.dist-info/METADATA
pydantic_filters-0.3.4.dist-info/WHEEL
pydantic_filters-0.3.4.dist-info/RECORD
