Metadata-Version: 2.1
Name: pydantic-filters
Version: 0.3.4
Summary: A declarative and intuitive way to describe data filtering and sorting in your application.
Home-page: https://github.com/so-saf/pydantic-filters
License: MIT
Keywords: pydantic,sqlalchemy,fastapi
Author: Nureev Insaf
Author-email: uneenymain@gmail.com
Requires-Python: >=3.8
Classifier: License :: OSI Approved :: MIT License
Classifier: Programming Language :: Python :: 3
Classifier: Programming Language :: Python :: 3.8
Classifier: Programming Language :: Python :: 3.9
Classifier: Programming Language :: Python :: 3.10
Classifier: Programming Language :: Python :: 3.11
Classifier: Programming Language :: Python :: 3.12
Requires-Dist: pydantic (>=2,<3)
Project-URL: Documentation, https://so-saf.github.io/pydantic-filters/
Project-URL: Repository, https://github.com/so-saf/pydantic-filters
